{
  "id": "calcharo",
  "name": "Calcharo",
  "aliases": [
    "卡卡罗"
  ],
  "element": "Electro",
  "weapon": "Broadblade",
  "faction": "Ghost Hounds",
  "rarity": 5,
  "releaseVersion": "1.0",
  "profile": "He is a former Exile from the New Federation's Lawless Zone and the leader of the Ghost Hounds.",
  "locale": "en-US",
  "source": {
    "sourceUrl": "https://wutheringwaves.fandom.com/wiki/Calcharo",
    "scrapedAt": "2026-06-02T19:30:43.185Z",
    "editor": "scripts/sync-fandom-data.ts"
  }
}
