{
  "id": "denia",
  "name": "Denia",
  "aliases": [
    "达妮娅"
  ],
  "element": "Fusion",
  "weapon": "Rectifier",
  "faction": "Fractsidus",
  "rarity": 5,
  "releaseVersion": "3.3",
  "profile": "She is a student from Startorch Academy's Department of Voidmatters who secretly serves as an agent for the Fractsidus. Created by Schwarzloch for the purpose to become a Threnodian Resonator, Denia can wear many faces.",
  "locale": "en-US",
  "source": {
    "sourceUrl": "https://wutheringwaves.fandom.com/wiki/Denia",
    "scrapedAt": "2026-06-02T19:30:43.185Z",
    "editor": "scripts/sync-fandom-data.ts"
  }
}
